{
    "$schema": "vscode://schemas/color-theme",
    "name": "Mystic-Cap",
    "uuid": "32818916-3391-4bb2-8fe3-8931b236bef5",
    "semanticHighlighting": true,
    "tokenColors": [
        {
            "scope": "comment",
            "settings": {
                "foreground": "#7f7e83",
                "fontStyle": "italic",
            }
        },
        {
            "scope": "punctuation",
            "settings": {
                "foreground": "#7f7e83",
            }
        },
        {
            "scope": "string",
            "settings": {
                "foreground": "#ffbd96"
            }
        },
        {
            "scope": "storage.modifier",
            "settings": {
                "foreground": "#FEDE5D"
            }
        },
        {
            "scope": [
                "storage.type",
                "support.type"
            ],
            "settings": {
                "foreground": "#d88c9a"
            }
        },
        {
            "scope": "constant",
            "settings": {
                "foreground": "#BAD761"
            }
        },
        {
            "scope": "entity",
            "settings": {
                "foreground": "#9cd1bb"
                // "foreground": "#9cc6d1"
            }
        },
        {
            "scope": "entity.name.type.class",
            "settings": {
                "foreground": "#9cc6d1"
            }
        },
        {
            "scope": "entity.name.tag",
            "settings": {
                "foreground": "#9cc6d1",
                "fontStyle": "italic"
            }
        },
        {
            "scope": [
                "entity.name.function",
                "support.function",
                "entity.name.method"
            ],
            "settings": {
                "foreground": "#88dba8",
                "fontStyle": "italic"
            }
        },
        {
            "scope": "entity.other",
            "settings": {
                "foreground": "#FF657A"
            }
        },
        {
            "scope": "variable",
            "settings": {
                "foreground": "#f0f0f0",
                "fontStyle": "italic"
            }
        },
        {
            "scope": "variable.language",
            "settings": {
                "foreground": "#9cd1bb",
                "fontStyle": "italic"
            }
        },
        {
            "scope": "variable.parameter",
            "settings": {
                "foreground": "#c39ac9",
                "fontStyle": "italic"
            }
        },
        {
            "scope": "variable.other.constant",
            "settings": {
                "foreground": "#d1c59c",
                "fontStyle": "italic"
            }
        },
        {
            "scope": "support",
            "settings": {
                "foreground": "#f0f0f0"
            }
        },
        {
            "scope": "strong",
            "settings": {
                "foreground": "#f0f0f0"
            }
        },
        {
            "scope": "meta",
            "settings": {
                "foreground": "#f0f0f0"
            }
        },
        {
            "scope": "markup",
            "settings": {
                "foreground": "#9cc6d1"
            }
        },
        {
            "scope": "emphasis",
            "settings": {
                "foreground": "#ffbd96"
            }
        },
        {
            "scope": "invalid",
            "settings": {
                "foreground": "#ff213f",
                "fontStyle": "strikethrough"
            }
        },
        {
            "scope": "keyword",
            "settings": {
                "foreground": "#FF657A",
                "fontStyle": "italic"
            }
        },
        {
            "scope": "keyword.operator",
            "settings": {
                "foreground": "#BAD761",
                "fontStyle": "italic"
            }
        },
    ],
    "colors": {
        "activityBar.activeFocusBorder": "#FFBD96",
        "activityBar.activeBorder": "#FFBD96",
        "activityBar.background": "#151523",
        "activityBar.border": "#0000",
        "activityBar.foreground": "#FFBD96",
        "activityBar.inactiveForeground": "#7f7e83",
        "activityBarBadge.background": "#FFBD96",
        "activityBarBadge.foreground": "#151523",
        "badge.background": "#FFBD96",
        "badge.foreground": "#151523",
        "banner.background": "#44455a",
        "banner.foreground": "#d9d9d9",
        "banner.iconForeground": "#c9c9c9",
        "breadcrumb.activeSelectionForeground": "#FFBD96",
        "breadcrumb.focusForeground": "#d9d9d9",
        "breadcrumb.foreground": "#7f7e83",
        "button.background": "#88dba8",
        "button.foreground": "#151523",
        "button.hoverBackground": "#32a47699",
        "button.secondaryBackground": "#383E4A",
        "button.secondaryForeground": "#c9c9c9",
        "button.secondaryHoverBackground": "#383E4A99",
        "button.separator": "#2c2d42",
        "charts.foreground": "#b9b9b9",
        "charts.yellow": "#FEDE5D",
        "checkbox.background": "#383E4A",
        "checkbox.border": "#151523",
        "checkbox.foreground": "#c9c9c9",
        "commandCenter.activeBackground": "#44455a",
        "commandCenter.activeForeground": "#d9d9d9",
        "commandCenter.background": "#2c2d42",
        "commandCenter.border": "#151523",
        "commandCenter.foreground": "#b9b9b9",
        "debugConsole.errorForeground": "#ff213f",
        "debugConsole.infoForeground": "#FFBD96",
        "debugConsole.sourceForeground": "#d9d9d9",
        "debugConsole.warningForeground": "#fea144",
        "debugConsoleInputIcon.foreground": "#FFBD96",
        "debugIcon.breakpointCurrentStackframeForeground": "#FFBD96",
        "debugIcon.breakpointDisabledForeground": "#b9b9b9",
        "debugIcon.breakpointForeground": "#FFBD96",
        "debugIcon.continueForeground": "#FFBD96",
        "debugIcon.disconnectForeground": "#ff213f",
        "debugIcon.pauseForeground": "#ffd152",
        "debugIcon.restartForeground": "#99c1b9",
        "debugIcon.startForeground": "#FFBD96",
        "debugIcon.stepIntoForeground": "#88dba8",
        "debugIcon.stepOutForeground": "#88dba8",
        "debugIcon.stepOverForeground": "#AA77FF",
        "debugIcon.stopForeground": "#ff213f",
        "debugTokenExpression.error": "#ff213f",
        "debugTokenExpression.string": "#FFBD96",
        "debugToolBar.background": "#44455a",
        "debugView.stateLabelBackground": "#44455a",
        "debugView.stateLabelForeground": "#d9d9d9",
        "debugView.valueChangedHighlight": "#FFBD96",
        "descriptionForeground": "#7f7e83",
        "disabledForeground": "#7f7e83",
        "dropdown.background": "#44455a",
        "dropdown.border": "#0000",
        "dropdown.foreground": "#d9d9d9",
        "dropdown.listBackground": "#44455a",
        "editor.background": "#2c2d42",
        "editor.findMatchBackground": "#FFBD9661",
        "editor.findMatchBorder": "#0000",
        "editor.findMatchHighlightBackground": "#0000",
        "editor.findMatchHighlightBorder": "#FFBD96",
        "editor.findRangeHighlightBackground": "#FFBD9639",
        "editor.findRangeHighlightBorder": "#adbc0e",
        "editor.focusedStackFrameHighlightBackground": "#e6ac0b39",
        "editor.foldBackground": "#383E4A99",
        "editor.foreground": "#f0f0f0",
        "editor.hoverHighlightBackground": "#383E4A",
        "editor.inactiveSelectionBackground": "#c9c9c919",
        "editor.inlineValuesBackground": "#44455a",
        "editor.inlineValuesForeground": "#d9d9d9",
        "editor.lineHighlightBackground": "#44455a77",
        "editor.lineHighlightBorder": "#0000",
        "editor.linkedEditingBackground": "#44455ac4",
        "editor.rangeHighlightBackground": "#FFBD9639",
        "editor.rangeHighlightBorder": "#0000",
        "editor.selectionBackground": "#c9c9c929",
        "editor.selectionHighlightBackground": "#0000",
        "editor.selectionHighlightBorder": "#7f7e83",
        "editor.stackFrameHighlightBackground": "#FFBD9639",
        "editor.wordHighlightBackground": "#FFBD9639",
        "editor.wordHighlightBorder": "#0000",
        "editor.wordHighlightStrongBackground": "#0000",
        "editor.wordHighlightStrongBorder": "#c9c9c9",
        "editorBracketHighlight.foreground1": "#ffac81",
        "editorBracketHighlight.foreground2": "#d88c9a",
        "editorBracketHighlight.foreground3": "#f2d0a9",
        "editorBracketHighlight.foreground4": "#f1e3d3",
        "editorBracketHighlight.foreground5": "#99c1b9",
        "editorBracketHighlight.foreground6": "#8e7dbe",
        "editorBracketMatch.background": "#0000",
        "editorBracketMatch.border": "#7f7e83",
        "editorCodeLens.foreground": "#7f7e83",
        "editorCursor.background": "#151523",
        "editorCursor.foreground": "#FFBD96",
        "editorError.background": "#44455a77",
        "editorError.border": "#0000",
        "editorError.foreground": "#ff213f",
        "editorGroup.border": "#151523",
        "editorGroup.dropBackground": "#44455a77",
        "editorGroup.emptyBackground": "#2c2d42",
        "editorGroup.focusedEmptyBorder": "#0000",
        /**/ "editorGroupHeader.noTabsBackground": "#1c1d32",
        /**/ "editorGroupHeader.tabsBackground": "#1c1d32",
        "editorGroupHeader.tabsBorder": "#0000",
        "editorGutter.addedBackground": "#88dba8",
        "editorGutter.background": "#0000",
        "editorGutter.deletedBackground": "#FE6244",
        "editorGutter.foldingControlForeground": "#b9b9b9",
        "editorGutter.modifiedBackground": "#FFBD96",
        "editorHoverWidget.background": "#44455a",
        "editorHoverWidget.border": "#0000",
        "editorIndentGuide.background1": "#7f7e8311",
        "editorIndentGuide.activeBackground2": "#7f7e8350",
        "editorLightBulb.foreground": "#c9c9c9",
        "editorLightBulbAutoFix.foreground": "#FFBD96",
        "editorLineNumber.activeForeground": "#FFBD96",
        "editorLineNumber.foreground": "#7f7e83",
        "editorLink.activeForeground": "#FFBD96",
        "editorOverviewRuler.addedForeground": "#88dba8",
        "editorOverviewRuler.currentContentForeground": "#ffe100",
        "editorOverviewRuler.deletedForeground": "#8f2d3a",
        "editorOverviewRuler.errorForeground": "#ff213f",
        "editorOverviewRuler.incomingContentForeground": "#fea144",
        "editorOverviewRuler.infoForeground": "#fea144",
        "editorOverviewRuler.modifiedForeground": "#D864A9",
        "editorOverviewRuler.rangeHighlightForeground": "#ffe100",
        "editorOverviewRuler.selectionHighlightForeground": "#ffe100",
        "editorOverviewRuler.warningForeground": "#fea144",
        "editorOverviewRuler.wordHighlightForeground": "#7652b0",
        "editorOverviewRuler.wordHighlightStrongForeground": "#AA77FF",
        "editorPane.background": "#151523",
        "editorSuggestWidget.background": "#44455a",
        "editorSuggestWidget.border": "#0000",
        "editorSuggestWidget.focusHighlightForeground": "#FFBD96",
        "editorSuggestWidget.foreground": "#b9b9b9",
        "editorSuggestWidget.highlightForeground": "#d9d9d9",
        "editorSuggestWidget.selectedForeground": "#d9d9d9",
        "editorSuggestWidget.selectedIconForeground": "#FFBD96",
        "editorSuggestWidget.selectedBackground": "#c9c9c929",
        "editorUnnecessaryCode.opacity": "#b9b9b977",
        "editorWarning.background": "#0000",
        "editorWarning.border": "#0000",
        "editorWarning.foreground": "#fea144",
        "editorWhitespace.foreground": "#7f7e83",
        "editorWidget.background": "#44455a",
        "editorWidget.border": "#0000",
        "errorForeground": "#ff213f",
        "extensionBadge.remoteBackground": "#88dba8",
        "extensionBadge.remoteForeground": "#151523",
        "extensionButton.prominentBackground": "#383E4A",
        "extensionButton.prominentForeground": "#c9c9c9",
        "extensionButton.prominentHoverBackground": "#383E4A99",
        "extensionIcon.preReleaseForeground": "#AA77FF",
        "extensionIcon.sponsorForeground": "#ff213f",
        "extensionIcon.starForeground": "#FFBD96",
        "extensionIcon.verifiedForeground": "#FFBD96",
        "focusBorder": "#7f7e8377",
        "foreground": "#b9b9b9",
        "gitDecoration.addedResourceForeground": "#88dba8",
        "gitDecoration.conflictingResourceForeground": "#ff213f",
        "gitDecoration.deletedResourceForeground": "#FE6244",
        "gitDecoration.ignoredResourceForeground": "#7f7e83",
        "gitDecoration.modifiedResourceForeground": "#d49571",
        "gitDecoration.renamedResourceForeground": "#D864A9",
        "gitDecoration.stageDeletedResourceForeground": "#62CDFF",
        "gitDecoration.stageModifiedResourceForeground": "#B5F1CC",
        "gitDecoration.submoduleResourceForeground": "#AA77FF",
        "gitDecoration.untrackedResourceForeground": "#a5a56e",
        "icon.foreground": "#b9b9b9",
        "input.background": "#151523",
        "input.border": "#7f7e83",
        "input.foreground": "#c9c9c9",
        "input.placeholderForeground": "#7f7e83",
        "inputOption.activeBackground": "#383E4A",
        "inputOption.activeBorder": "#0000",
        "inputOption.activeForeground": "#FFBD96",
        "inputOption.hoverBackground": "#383E4A99",
        "inputValidation.errorBorder": "#ff213f",
        "inputValidation.errorForeground": "#ff213f",
        "inputValidation.infoBorder": "#c9c9c9",
        "inputValidation.infoForeground": "#c9c9c9",
        "inputValidation.warningBackground": "#0000",
        "inputValidation.warningBorder": "#0000",
        "inputValidation.warningForeground": "#fea144",
        "keybindingLabel.background": "#44455a",
        "keybindingLabel.border": "#0000",
        "keybindingLabel.bottomBorder": "#7f7e83",
        "keybindingLabel.foreground": "#d9d9d9",
        "list.activeSelectionBackground": "#88dba8",
        "list.activeSelectionForeground": "#151523",
        "list.focusBackground": "#32a476cc",
        "list.focusForeground": "#151523",
        "list.hoverBackground": "#44455a",
        "list.hoverForeground": "#FFBD96",
        "list.inactiveFocusBackground": "#151523",
        "list.inactiveSelectionBackground": "#0000",
        "list.inactiveSelectionForeground": "#d9d9d9",
        "list.inactiveSelectionIconForeground": "#b9b9b9",
        "list.invalidItemForeground": "#ff213f",
        "list.warningForeground": "#fea144",
        "menu.background": "#44455a",
        "menu.border": "#0000",
        "menu.foreground": "#d9d9d9",
        "menu.selectionForeground": "#151523",
        "menu.separatorBackground": "#c9c9c9",
        "menubar.selectionForeground": "#d9d9d9",
        "notificationCenterHeader.foreground": "#d9d9d9",
        "notificationLink.foreground": "#FFBD96",
        "notificationsErrorIcon.foreground": "#ff213f",
        "notificationsInfoIcon.foreground": "#c9c9c9",
        "notificationsWarningIcon.foreground": "#fea144",
        "panel.background": "#44455a",
        "panel.border": "#0000",
        "panelTitle.activeBorder": "#FFBD96",
        "panelTitle.activeForeground": "#e9e9e9",
        "panelTitle.inactiveForeground": "#b9b9b9",
        "ports.iconRunningProcessForeground": "#FFBD96",
        "problemsErrorIcon.foreground": "#ff213f",
        "problemsInfoIcon.foreground": "#c9c9c9",
        "problemsWarningIcon.foreground": "#fea144",
        "progressBar.background": "#FFBD96",
        "scrollbar.shadow": "#0000",
        "scrollbarSlider.activeBackground": "#c9c9c929",
        "scrollbarSlider.background": "#44455a99",
        "selection.background": "#88dba857",
        "settings.headerForeground": "#FFBD96",
        "settings.modifiedItemIndicator": "#FFBD96",
        "settings.rowHoverBackground": "#44455a",
        "sideBar.background": "#1c1d32",
        "sideBar.foreground": "#b9b9b9",
        "sideBarSectionHeader.background": "#0000",
        "sideBarSectionHeader.foreground": "#c9c9c9",
        "sideBarTitle.foreground": "#FFBD96",
        "statusBar.background": "#44455a",
        "statusBar.debuggingBackground": "#FFBD96",
        "statusBar.debuggingForeground": "#151523",
        "statusBar.foreground": "#d9d9d9",
        "statusBar.noFolderBackground": "#1c1d32",
        "statusBar.noFolderForeground": "#d9d9d9",
        "statusBarItem.errorForeground": "#ff213f",
        "statusBarItem.prominentBackground": "#383E4A",
        "statusBarItem.prominentHoverBackground": "#c9c9c9",
        "statusBarItem.remoteBackground": "#88dba8",
        "statusBarItem.remoteForeground": "#151523",
        "statusBarItem.warningForeground": "#fea144",
        "tab.activeBackground": "#2c2d42",
        /**/ "tab.activeBorderTop": "#FFBD96",
        "tab.activeForeground": "#FFBD96",
        "tab.activeModifiedBorder": "#c9c9c9",
        "tab.border": "#0000",
        "tab.hoverBackground": "#44455a",
        /**/ "tab.hoverBorder": "#0000",
        "tab.hoverForeground": "#d9d9d9",
        /**/ "tab.inactiveBackground": "#1c1d32",
        "tab.inactiveForeground": "#b9b9b9",
        "tab.inactiveModifiedBorder": "#b9b9b9",
        "tab.lastPinnedBorder": "#FFBD96",
        "tab.unfocusedActiveBorder": "#c9c9c9",
        "tab.unfocusedActiveForeground": "#b9b9b9",
        "tab.unfocusedActiveModifiedBorder": "#7f7e83",
        "tab.unfocusedHoverBackground": "#44455a",
        "tab.unfocusedHoverBorder": "#0000",
        "tab.unfocusedHoverForeground": "#d9d9d9",
        "tab.unfocusedInactiveForeground": "#7f7e83",
        "tab.unfocusedInactiveModifiedBorder": "#0000",
        "terminal.ansiBlack": "#151523",
        "terminal.ansiBlue": "#19A7CE",
        "terminal.ansiBrightBlack": "#383E4A",
        "terminal.ansiBrightBlue": "#62CDFF",
        "terminal.ansiBrightCyan": "#C9EEFF",
        "terminal.ansiBrightGreen": "#B5F1CC",
        "terminal.ansiBrightMagenta": "#AA77FF",
        "terminal.ansiBrightRed": "#FE6244",
        "terminal.ansiBrightWhite": "#ffffff",
        "terminal.ansiBrightYellow": "#f4df8e",
        "terminal.ansiCyan": "#85CDFD",
        "terminal.ansiGreen": "#88dba8",
        "terminal.ansiMagenta": "#D864A9",
        "terminal.ansiRed": "#ff213f",
        "terminal.ansiWhite": "#c9c9c9",
        "terminal.ansiYellow": "#FEDE5D",
        "terminal.background": "#44455a",
        "terminal.foreground": "#d9d9d9",
        "terminal.selectionBackground": "#FFBD9639",
        "terminalCommandDecoration.defaultBackground": "#FFBD96",
        "terminalCommandDecoration.errorBackground": "#ff213f",
        "terminalCommandDecoration.successBackground": "#88dba8",
        "terminalCursor.background": "#151523",
        "terminalCursor.foreground": "#FFBD96",
        "testing.iconErrored": "#ff213f",
        "testing.runAction": "#FFBD96",
        "textLink.activeForeground": "#88dba8",
        "textLink.foreground": "#FFBD96",
        "textPreformat.foreground": "#FFBD96",
        "titleBar.activeBackground": "#151523",
        "titleBar.activeForeground": "#b9b9b9",
        "titleBar.inactiveBackground": "#151523",
        "titleBar.inactiveForeground": "#b9b9b9",
        "welcomePage.progress.background": "#7f7e83",
        "welcomePage.progress.foreground": "#FFBD96",
        "welcomePage.tileBackground": "#44455a",
        "welcomePage.tileHoverBackground": "#44455a77",
        "widget.shadow": "#151523"
    },
}